odoo/addons/sale_cancel_restrict/README.rst
odoo/addons/sale_cancel_restrict/__init__.py
odoo/addons/sale_cancel_restrict/__manifest__.py
odoo/addons/sale_cancel_restrict/i18n/it.po
odoo/addons/sale_cancel_restrict/i18n/sale_cancel_restrict.pot
odoo/addons/sale_cancel_restrict/models/__init__.py
odoo/addons/sale_cancel_restrict/models/res_company.py
odoo/addons/sale_cancel_restrict/models/res_config_settings.py
odoo/addons/sale_cancel_restrict/models/sale_order.py
odoo/addons/sale_cancel_restrict/readme/CONTRIBUTORS.md
odoo/addons/sale_cancel_restrict/readme/DESCRIPTION.md
odoo/addons/sale_cancel_restrict/readme/USAGE.md
odoo/addons/sale_cancel_restrict/static/description/icon.png
odoo/addons/sale_cancel_restrict/static/description/index.html
odoo/addons/sale_cancel_restrict/tests/__init__.py
odoo/addons/sale_cancel_restrict/tests/test_sale_cancel_restrict.py
odoo/addons/sale_cancel_restrict/views/res_config_settings_views.xml
odoo_addon_sale_cancel_restrict-19.0.1.0.0.4.dist-info/METADATA
odoo_addon_sale_cancel_restrict-19.0.1.0.0.4.dist-info/WHEEL
odoo_addon_sale_cancel_restrict-19.0.1.0.0.4.dist-info/top_level.txt
odoo_addon_sale_cancel_restrict-19.0.1.0.0.4.dist-info/RECORD
